backbones/__init__.py
backbones/__main__.py
backbones/_cli.py
backbones/_export.py
backbones/_features.py
backbones/_interface.py
backbones/_io.py
backbones/_normalize.py
backbones/py.typed
backbones/resnet/__init__.py
backbones/resnet/_cli.py
backbones/resnet/_modules.py
backbones/resnet/configs.py
backbones/swin/__init__.py
backbones/swin/configs.py
backbones/timm.py
backbones/torchvision.py
backbones-0.0.2.dist-info/WHEEL
backbones-0.0.2.dist-info/entry_points.txt
backbones-0.0.2.dist-info/METADATA
backbones-0.0.2.dist-info/RECORD
