Metadata-Version: 2.3
Name: backbones
Version: 0.0.2
Summary: Backbone networks for computer vision research.
Keywords: perception,computer vision,deep learning,object detection,instance segmentation,semantic segmentation
Author: Kurt Stolle
Author-email: Kurt Stolle <kurt@khws.io>
Classifier: Development Status :: 4 - Beta
Classifier: Programming Language :: Python
Classifier: Programming Language :: Python :: 3.12
Classifier: Programming Language :: Python :: 3.13
Classifier: Programming Language :: Python :: Implementation :: CPython
Requires-Dist: torch>=2.6.0
Requires-Dist: torchvision
Requires-Dist: safetensors
Requires-Dist: regex
Requires-Dist: laco
Requires-Dist: expath
Requires-Dist: sphinx ; extra == 'docs'
Requires-Dist: sphinx-rtd-theme ; extra == 'docs'
Requires-Dist: numpydoc ; extra == 'docs'
Requires-Dist: jupyterlab ; extra == 'notebooks'
Requires-Dist: ipywidgets ; extra == 'notebooks'
Requires-Dist: ipykernel ; extra == 'notebooks'
Requires-Dist: ipython-autotime ; extra == 'notebooks'
Requires-Dist: hypothesis ; extra == 'tests'
Requires-Dist: bandit[toml] ; extra == 'tests'
Requires-Dist: check-manifest ; extra == 'tests'
Requires-Dist: ruff ; extra == 'tests'
Requires-Dist: pre-commit ; extra == 'tests'
Requires-Dist: pytest ; extra == 'tests'
Requires-Dist: pytest-sugar ; extra == 'tests'
Requires-Dist: pytest-xdist ; extra == 'tests'
Requires-Dist: pytest-benchmark ; extra == 'tests'
Requires-Dist: pytest-cov ; extra == 'tests'
Requires-Dist: pytest-mock ; extra == 'tests'
Requires-Dist: pytest-runner ; extra == 'tests'
Requires-Dist: mccabe ; extra == 'tests'
Requires-Dist: timm ; extra == 'timm'
Requires-Dist: torchvision ; extra == 'torchvision'
Requires-Python: >=3.12
Provides-Extra: docs
Provides-Extra: notebooks
Provides-Extra: tests
Provides-Extra: timm
Provides-Extra: torchvision
